<?xml version="1.0" encoding="UTF-8"?>
<objects serializationModel="Studio.02.03.00">
	<object class="AudioFile" id="{d3bc11e4-2cd4-4f5b-b024-60873c79bd92}">
		<property name="assetPath">
			<value>ambi.mp3</value>
		</property>
		<property name="frequencyInKHz">
			<value>48</value>
		</property>
		<property name="channelCount">
			<value>2</value>
		</property>
		<property name="length">
			<value>8.9280000000000008</value>
		</property>
		<relationship name="masterAssetFolder">
			<destination>{771fede4-2437-456d-afeb-b44ba2477689}</destination>
		</relationship>
	</object>
</objects>
